pgd.py
PGD-0.0.2.dist-info/METADATA
PGD-0.0.2.dist-info/WHEEL
PGD-0.0.2.dist-info/top_level.txt
PGD-0.0.2.dist-info/RECORD
