Metadata-Version: 2.1
Name: PGD
Version: 0.0.2
Summary: it can detect gender by firstName
Home-page: UNKNOWN
Author: Hamed Pariazar
License: UNKNOWN
Platform: UNKNOWN
Classifier: Programming Language :: Python :: 3
Classifier: License :: OSI Approved :: MIT License
Classifier: Operating System :: OS Independent
Requires-Python: >=3.6
